s1290080_learn/__init__.py
s1290080_learn/statistics/__init__.py
s1290080_learn/statistics/frequenciesOfItems.py
s1290080_learn/visualization/__init__.py
s1290080_learn/visualization/heatMapItemsFrequencies.py
s1290080_learn-1.0.1.dist-info/LICENSE.txt
s1290080_learn-1.0.1.dist-info/METADATA
s1290080_learn-1.0.1.dist-info/WHEEL
s1290080_learn-1.0.1.dist-info/top_level.txt
s1290080_learn-1.0.1.dist-info/RECORD
